[
  {
    "cat": "getting-started",
    "catTitle": "Getting Started",
    "docs": [
      {
        "doc": "introduction",
        "title": "Introduction",
        "description": "Introduction to Begin",
        "github": "https://github.com/smallwins/docs.begin.com/blob/master/src/shared/docs/en/getting-started/introduction.md",
        "nextDoc": "/en/getting-started/quickstart/",
        "nextTitle": "Quickstart",
        "sections": [
          {
            "anchor": "#what-is-begin-",
            "name": "What is Begin?"
          },
          {
            "anchor": "#what-begin-does-doesn-t-do",
            "name": "What Begin does & doesn't do"
          },
          {
            "anchor": "#background-open-source-governance",
            "name": "Background & open source governance"
          }
        ]
      },
      {
        "doc": "quickstart",
        "title": "Quickstart",
        "description": "Get started building your first app with Begin",
        "github": "https://github.com/smallwins/docs.begin.com/blob/master/src/shared/docs/en/getting-started/quickstart.md",
        "nextDoc": "/en/getting-started/working-locally/",
        "nextTitle": "Working locally",
        "sections": [
          {
            "anchor": "#prerequisites",
            "name": "Prerequisites"
          },
          {
            "anchor": "#create-a-begin-account",
            "name": "Create a Begin account"
          },
          {
            "anchor": "#creating-an-app",
            "name": "Creating an app"
          },
          {
            "anchor": "#your-first-deploy",
            "name": "Your first deploy"
          },
          {
            "anchor": "#accessing-your-live-app",
            "name": "Accessing your live app"
          },
          {
            "anchor": "#project-structure",
            "name": "Project structure"
          },
          {
            "anchor": "#working-locally",
            "name": "Working locally"
          },
          {
            "anchor": "#keep-it-going",
            "name": "Keep it going"
          }
        ]
      },
      {
        "doc": "working-locally",
        "title": "Working locally",
        "description": "Guide to working locally and writing tests with Begin",
        "github": "https://github.com/smallwins/docs.begin.com/blob/master/src/shared/docs/en/getting-started/working-locally.md",
        "nextDoc": "/en/getting-started/builds-deploys/",
        "nextTitle": "Building & deploying",
        "sections": [
          {
            "anchor": "#overview",
            "name": "Overview"
          },
          {
            "anchor": "#getting-set-up",
            "name": "Getting set up"
          },
          {
            "anchor": "#working-with-routes",
            "name": "Working with routes"
          },
          {
            "anchor": "#writing-tests",
            "name": "Writing tests"
          }
        ]
      },
      {
        "doc": "builds-deploys",
        "title": "Building & deploying",
        "description": "Guide to creating new builds and deploying them to Begin",
        "github": "https://github.com/smallwins/docs.begin.com/blob/master/src/shared/docs/en/tktk/tktk.md",
        "nextDoc": "/en/getting-started/environments/",
        "nextTitle": "Environment variables",
        "sections": [
          {
            "anchor": "#overview",
            "name": "Overview"
          },
          {
            "anchor": "#build-pipeline",
            "name": "Build pipeline"
          },
          {
            "anchor": "#deploying-to-staging",
            "name": "Deploying to staging"
          },
          {
            "anchor": "#deploying-to-production",
            "name": "Deploying to production"
          },
          {
            "anchor": "#configuring-build-steps",
            "name": "Configuring build steps"
          }
        ]
      },
      {
        "doc": "environments",
        "title": "Environment variables",
        "description": "Configuring your Begin app's environment variables",
        "github": "https://github.com/smallwins/docs.begin.com/blob/master/src/shared/docs/en/getting-started/environments.md",
        "nextDoc": "/en/getting-started/domains/",
        "nextTitle": "Domain names",
        "sections": [
          {
            "anchor": "#overview",
            "name": "Overview"
          },
          {
            "anchor": "#adding-variables",
            "name": "Adding variables"
          },
          {
            "anchor": "#editing variables",
            "name": "Editing variables"
          }
        ]
      },
      {
        "doc": "domains",
        "title": "Domain names",
        "description": "Configuring your Begin app's domain",
        "github": "https://github.com/smallwins/docs.begin.com/blob/master/src/shared/docs//en/getting-started/domains.md",
        "nextDoc": "/en/getting-started/static-assets/",
        "nextTitle": "Settings",
        "sections": [
          {
            "anchor": "#overview",
            "name": "Overview"
          },
          {
            "anchor": "#mapping-your-domain",
            "name": "Mapping your domain"
          },
          {
            "anchor": "#generating-ssl-certificates",
            "name": "Generating SSL certificates"
          },
          {
            "anchor": "#domain-mapping",
            "name": "Domain mapping"
          },
          {
            "anchor": "#mapping-naked-domains",
            "name": "Mapping naked domains"
          }
        ]
      },
      {
        "doc": "static-assets",
        "title": "Static assets",
        "description": "Building, deploying, and accessing static assets from Begin",
        "github": "https://github.com/smallwins/docs.begin.com/blob/master/src/shared/docs/en/getting-started/static-assets.md",
        "nextDoc": "/en/getting-started/settings/",
        "nextTitle": "Settings",
        "sections": [
          {
            "anchor": "#overview",
            "name": "Overview"
          },
          {
            "anchor": "#the-static-directory",
            "name": "The .static directory"
          },
          {
            "anchor": "#building-and-deploying-assets",
            "name": "Building and deploying assets"
          },
          {
            "anchor": "#accessing-static-assets",
            "name": "Accessing static assets"
          }
        ]
      },
      {
        "doc": "settings",
        "title": "Settings",
        "description": "Configuring your Begin app's settings",
        "github": "https://github.com/smallwins/docs.begin.com/blob/master/src/shared/docs//en/getting-started/settings.md",
        "nextDoc": "/en/functions/creating-new-functions/",
        "nextTitle": "Creating new functions",
        "sections": [
          {
            "anchor": "#overview",
            "name": "Overview"
          },
          {
            "anchor": "#app-name",
            "name": "App name"
          },
          {
            "anchor": "#notifications",
            "name": "Notifications"
          },
          {
            "anchor": "#aws-resources-inventory",
            "name": "AWS resources inventory"
          },
          {
            "anchor": "#deleting-your-app",
            "name": "Deleting your app"
          },
          {
            "anchor": "#ejecting-your-app",
            "name": "Ejecting your app"
          }
        ]
      }
    ]
  },
  {
    "cat": "functions",
    "catTitle": "Functions",
    "docs": [
      {
        "doc": "creating-new-functions",
        "title": "Creating new functions",
        "description": "Creating new functions for your Begin application",
        "github": "https://github.com/smallwins/docs.begin.com/blob/master/src/shared/docs/en/functions/creating-new-http-functions.md",
        "nextDoc": "/en/functions/sessions/",
        "nextTitle": "Sessions",
        "sections": [
          {
            "anchor": "#overview",
            "name": "Overview"
          },
          {
            "anchor": "#using-url-parameters-to-create-dynamic-paths",
            "name": "Using URL parameters to create dynamic paths"
          },
          {
            "anchor": "#more-about-routes-in-begin",
            "name": "More about routes in Begin"
          }
        ]
      },
      {
        "doc": "sessions",
        "title": "Sessions",
        "description": "Using Begin's built-in sessions support",
        "github": "https://github.com/smallwins/docs.begin.com/blob/master/src/shared/docs/en/functions/sessions.md",
        "nextDoc": "/en/functions/html-routes/",
        "nextTitle": "HTML Routes",
        "sections": [
          {
            "anchor": "#overview",
            "name": "Overview"
          },
          {
            "anchor": "#writing-to-sessions",
            "name": "Writing to sessions"
          },
          {
            "anchor": "#more-about-sessions",
            "name": "More about sessions"
          },
          {
            "anchor": "#examples",
            "name": "Examples"
          }
        ]
      },
      {
        "doc": "html-routes",
        "title": "HTML Routes",
        "description": "Building HTML routes for your Begin application",
        "github": "https://github.com/smallwins/docs.begin.com/blob/master/src/shared/docs/en/functions/html-routes.md",
        "nextDoc": "/en/functions/json-routes/",
        "nextTitle": "JSON Routes",
        "sections": [
          {
            "anchor": "#overview",
            "name": "Overview"
          },
          {
            "anchor": "#get-routes",
            "name": "GET routes"
          },
          {
            "anchor": "#get-examples",
            "name": "GET examples"
          },
          {
            "anchor": "#post-routes",
            "name": "POST routes"
          },
          {
            "anchor": "#post-examples",
            "name": "POST examples"
          },
          {
            "anchor": "#custom-error-pages",
            "name": "Custom error pages"
          }
        ]
      },
      {
        "doc": "json-routes",
        "title": "JSON Routes",
        "description": "Building JSON routes for your Begin application",
        "github": "https://github.com/smallwins/docs.begin.com/blob/master/src/shared/docs/en/functions/json-routes.md",
        "nextDoc": "/en/functions/xml-routes/",
        "nextTitle": "XML Routes",
        "sections": [
          {
            "anchor": "#overview",
            "name": "Overview"
          },
          {
            "anchor": "#get-routes",
            "name": "GET routes"
          },
          {
            "anchor": "#get-examples",
            "name": "GET examples"
          },
          {
            "anchor": "#post-routes",
            "name": "POST routes"
          },
          {
            "anchor": "#post-examples",
            "name": "POST examples"
          },
          {
            "anchor": "#put-routes",
            "name": "PUT routes"
          },
          {
            "anchor": "#put-examples",
            "name": "PUT examples"
          },
          {
            "anchor": "#patch-routes",
            "name": "PATCH routes"
          },
          {
            "anchor": "#patch-examples",
            "name": "PATCH examples"
          },
          {
            "anchor": "#delete-routes",
            "name": "DELETE routes"
          },
          {
            "anchor": "#delete-examples",
            "name": "DELETE examples"
          }
        ]
      },
      {
        "doc": "xml-routes",
        "title": "XML Routes",
        "description": "Building XML routes for your Begin application",
        "github": "https://github.com/smallwins/docs.begin.com/blob/master/src/shared/docs/en/functions/xml-routes.md",
        "nextDoc": "/en/functions/css-routes/",
        "nextTitle": "CSS Routes",
        "sections": [
          {
            "anchor": "#overview",
            "name": "Overview"
          },
          {
            "anchor": "#get-routes",
            "name": "GET routes"
          },
          {
            "anchor": "#get-examples",
            "name": "GET examples"
          },
          {
            "anchor": "#post-routes",
            "name": "POST routes"
          },
          {
            "anchor": "#post-examples",
            "name": "POST examples"
          },
          {
            "anchor": "#put-routes",
            "name": "PUT routes"
          },
          {
            "anchor": "#put-examples",
            "name": "PUT examples"
          },
          {
            "anchor": "#patch-routes",
            "name": "PATCH routes"
          },
          {
            "anchor": "#patch-examples",
            "name": "PATCH examples"
          },
          {
            "anchor": "#delete-routes",
            "name": "DELETE routes"
          },
          {
            "anchor": "#delete-examples",
            "name": "DELETE examples"
          }
        ]
      },
      {
        "doc": "css-routes",
        "title": "CSS Routes",
        "description": "Building CSS routes for your Begin application",
        "github": "https://github.com/smallwins/docs.begin.com/blob/master/src/shared/docs/en/functions/css-routes.md",
        "nextDoc": "/en/functions/javascript-routes/",
        "nextTitle": "JavaScript Routes",
        "sections": [
          {
            "anchor": "#overview",
            "name": "Overview"
          },
          {
            "anchor": "#begin-css-get-",
            "name": "begin.css.get()"
          },
          {
            "anchor": "#get-examples",
            "name": "GET examples"
          }
        ]
      },
      {
        "doc": "javascript-routes",
        "title": "JavaScript Routes",
        "description": "Building JavaScript routes for your Begin application",
        "github": "https://github.com/smallwins/docs.begin.com/blob/master/src/shared/docs/en/functions/javascript-routes.md",
        "nextDoc": "/en/functions/text-routes/",
        "nextTitle": "Text Routes",
        "sections": [
          {
            "anchor": "#overview",
            "name": "Overview"
          },
          {
            "anchor": "#begin-js-get-",
            "name": "begin.js.get()"
          },
          {
            "anchor": "#get-examples",
            "name": "GET examples"
          }
        ]
      },
      {
        "doc": "text-routes",
        "title": "Text Routes",
        "description": "Building text routes for your Begin application",
        "github": "https://github.com/smallwins/docs.begin.com/blob/master/src/shared/docs/en/functions/text-routes.md",
        "nextDoc": "/en/functions/events/",
        "nextTitle": "Events",
        "sections": [
          {
            "anchor": "#overview",
            "name": "Overview"
          },
          {
            "anchor": "#begin-text-get-",
            "name": "begin.text.get()"
          },
          {
            "anchor": "#get-examples",
            "name": "GET examples"
          }
        ]
      },
      {
        "doc": "events",
        "title": "Events",
        "description": "Creating new events for your Begin application",
        "github": "https://github.com/smallwins/docs.begin.com/blob/master/src/shared/docs/en/functions/events.md",
        "nextDoc": "/en/functions/scheduled/",
        "nextTitle": "Scheduled",
        "sections": [
          {
            "anchor": "#overview",
            "name": "Overview"
          }
        ]
      },
      {
        "doc": "scheduled",
        "title": "Scheduled",
        "description": "Creating new schedules for your Begin application",
        "github": "https://github.com/smallwins/docs.begin.com/blob/master/src/shared/docs/en/functions/schedules.md",
        "nextDoc": "/en/functions/queues/",
        "nextTitle": "Queues",
        "sections": [
          {
            "anchor": "#overview",
            "name": "Overview"
          }
        ]
      },
      {
        "doc": "queues",
        "title": "Queues",
        "description": "Creating new queues for your Begin application",
        "github": "https://github.com/smallwins/docs.begin.com/blob/master/src/shared/docs/en/functions/creating-new-queues.md",
        "nextDoc": "/en/support/help-support",
        "nextTitle": "Help & support",
        "sections": [
          {
            "anchor": "#overview",
            "name": "Overview"
          }
        ]
      }
    ]
  },
  {
    "cat": "support",
    "catTitle": "Support",
    "docs": [
      {
        "doc": "help-support",
        "title": "Help & support",
        "description": "Help & support channels for Begin",
        "github": "https://github.com/smallwins/docs.begin.com/blob/master/src/shared/docs/en/support/help-support.md",
        "nextDoc": "/en/support/issues",
        "nextTitle": "Issues & feature requests"
      },
      {
        "doc": "issues",
        "title": "Issues & feature requests",
        "description": "How and where to file issues and feature requests for Begin",
        "github": "https://github.com/smallwins/docs.begin.com/blob/master/src/shared/docs/en/support/issues.md",
        "nextDoc": "/en/meta/about",
        "nextTitle": "About Begin"
      }
    ]
  },
  {
    "cat": "meta",
    "catTitle": "Meta",
    "docs": [
      {
        "doc": "about",
        "title": "About Begin",
        "description": "About Begin: who we are, what we believe, how Begin works",
        "github": "https://github.com/smallwins/docs.begin.com/blob/master/src/shared/docs/en/meta/support.md",
        "//nextDoc": "",
        "//nextTitle": "",
        "sections": [
          {
            "anchor": "#overview",
            "name": "Who we are"
          },
          {
            "anchor": "#begin-text-get-",
            "name": "What we believe"
          },
          {
            "anchor": "#get-examples",
            "name": "Our business model"
          }
        ]
      }
    ]
  }
]
